jetblack_asgi_sspi/__init__.py
jetblack_asgi_sspi/py.typed
jetblack_asgi_sspi/session_manager.py
jetblack_asgi_sspi/spnego_middleware.py
jetblack_asgi_sspi-1.0.0rc0.dist-info/LICENSE
jetblack_asgi_sspi-1.0.0rc0.dist-info/WHEEL
jetblack_asgi_sspi-1.0.0rc0.dist-info/METADATA
jetblack_asgi_sspi-1.0.0rc0.dist-info/RECORD
